byted_overpass_ddaa_scan_scope_manager/__init__.py
byted_overpass_ddaa_scan_scope_manager-0.0.1.dist-info/METADATA
byted_overpass_ddaa_scan_scope_manager-0.0.1.dist-info/WHEEL
byted_overpass_ddaa_scan_scope_manager-0.0.1.dist-info/top_level.txt
byted_overpass_ddaa_scan_scope_manager-0.0.1.dist-info/RECORD
